{
  "universities": [
    {
      "id": 1,
      "name": "Universidade de São Paulo (USP)",
      "site": "https://www5.usp.br/",
      "state": "São Paulo",
      "type": "pública"
    },
    {
      "id": 2,
      "name": "Universidade Federal do Rio de Janeiro (UFRJ)",
      "site": "https://ufrj.br/",
      "state": "Rio de Janeiro",
      "type": "pública"
    },
    {
      "id": 3,
      "name": "Pontifícia Universidade Católica do Rio de Janeiro (PUC-Rio)",
      "site": "https://www.puc-rio.br/",
      "state": "Rio de Janeiro",
      "type": "privada"
    },
    {
      "id": 4,
      "name": "Universidade Estadual de Campinas (UNICAMP)",
      "site": "https://www.unicamp.br/",
      "state": "São Paulo",
      "type": "pública"
    },
    {
      "id": 5,
      "name": "Universidade Federal de Minas Gerais (UFMG)",
      "site": "https://www.ufmg.br/",
      "state": "Minas Gerais",
      "type": "pública"
    },
    {
      "id": 7,
      "name": "Universidade de Brasília (UnB)",
      "site": "https://www.unb.br/",
      "state": "Distrito Federal",
      "type": "pública"
    },
    {
      "id": 8,
      "name": "Universidade Federal de Santa Catarina (UFSC)",
      "site": "https://www.ufsc.br/",
      "state": "Santa Catarina",
      "type": "pública"
    },
    {
      "id": 9,
      "name": "Universidade Federal do Paraná (UFPR)",
      "site": "https://www.ufpr.br/",
      "state": "Paraná",
      "type": "pública"
    },
    {
      "id": 10,
      "name": "Universidade Federal de Pernambuco (UFPE)",
      "site": "https://www.ufpe.br/",
      "state": "Pernambuco",
      "type": "pública"
    },
    {
      "id": 11,
      "name": "Universidade Federal do Rio Grande do Sul (UFRGS)",
      "site": "https://www.ufrgs.br/",
      "state": "Rio Grande do Sul",
      "type": "pública"
    },
    {
      "id": 12,
      "name": "Universidade Federal do Pará (UFPA)",
      "site": "https://www.ufpa.br/",
      "state": "Pará",
      "type": "pública"
    },
    {
      "id": 13,
      "name": "Universidade Federal de São Paulo (UNIFESP)",
      "site": "https://www.unifesp.br/",
      "state": "São Paulo",
      "type": "pública"
    },
    {
      "id": 14,
      "name": "Universidade Federal de Goiás (UFG)",
      "site": "https://www.ufg.br/",
      "state": "Goiás",
      "type": "pública"
    },
    {
      "id": 15,
      "name": "Universidade Federal de Uberlândia (UFU)",
      "site": "https://www.ufu.br/",
      "state": "Minas Gerais",
      "type": "pública"
    },
    {
      "id": 16,
      "name": "Universidade Federal de Viçosa (UFV)",
      "site": "https://www.ufv.br/",
      "state": "Minas Gerais",
      "type": "pública"
    },
    {
      "id": 17,
      "name": "Universidade Federal de Juiz de Fora (UFJF)",
      "site": "https://www.ufjf.br/",
      "state": "Minas Gerais",
      "type": "pública"
    },
    {
      "id": 18,
      "name": "Universidade Federal de São Carlos (UFSCar)",
      "site": "https://www2.ufscar.br/",
      "state": "São Paulo",
      "type": "pública"
    },
    {
      "id": 19,
      "name": "Universidade Federal de Itajubá (UNIFEI)",
      "site": "https://www.unifei.edu.br/",
      "state": "Minas Gerais",
      "type": "pública"
    },
    {
      "id": 20,
      "name": "Universidade Federal de Ouro Preto (UFOP)",
      "site": "https://www.ufop.br/",
      "state": "Minas Gerais",
      "type": "pública"
    },
    {
      "id": 21,
      "name": "Universidade Federal do ABC (UFABC)",
      "site": "https://www.ufabc.edu.br/",
      "state": "São Paulo",
      "type": "pública"
    },
    {
      "id": 22,
      "name": "Universidade Federal do Espírito Santo (UFES)",
      "site": "https://www.ufes.br/",
      "state": "Espírito Santo",
      "type": "pública"
    },
    {
      "id": 23,
      "name": "Universidade Federal de Lavras (UFLA)",
      "site": "https://ufla.br/",
      "state": "Minas Gerais",
      "type": "pública"
    },
    {
      "id": 24,
      "name": "Universidade Federal de Sergipe (UFS)",
      "site": "https://www.ufs.br/",
      "state": "Sergipe",
      "type": "pública"
    },
    {
      "id": 25,
      "name": "Universidade Federal do Maranhão (UFMA)",
      "site": "https://portais.ufma.br/",
      "state": "Maranhão",
      "type": "pública"
    },
    {
      "id": 26,
      "name": "Universidade Federal do Rio Grande do Norte (UFRN)",
      "site": "https://www.ufrn.br/",
      "state": "Rio Grande do Norte",
      "type": "pública"
    },
    {
      "id": 27,
      "name": "Universidade Federal da Bahia (UFBA)",
      "site": "https://www.ufba.br/",
      "state": "Bahia",
      "type": "pública"
    },
    {
      "id": 28,
      "name": "Universidade Federal de Santa Maria (UFSM)",
      "site": "https://www.ufsm.br/",
      "state": "Rio Grande do Sul",
      "type": "pública"
    },
    {
      "id": 29,
      "name": "Universidade Federal do Amazonas (UFAM)",
      "site": "https://www.ufam.edu.br/",
      "state": "Amazonas",
      "type": "pública"
    },
    {
      "id": 30,
      "name": "Universidade Federal do Piauí (UFPI)",
      "site": "https://www.ufpi.br/",
      "state": "Piauí",
      "type": "pública"
    },
    {
      "id": 31,
      "name": "Universidade Federal de Alagoas (UFAL)",
      "site": "https://www.ufal.br/",
      "state": "Alagoas",
      "type": "pública"
    },
    {
      "id": 32,
      "name": "Universidade Federal do Ceará (UFC)",
      "site": "https://prograd.ufc.br/pt/cursos-de-graduacao/",
      "state": "Ceará",
      "type": "pública"
    },
    {
      "id": 33,
      "name": "Universidade Federal do Espírito Santo (UFES)",
      "site": "https://www.ufes.br/",
      "state": "Espírito Santo",
      "type": "pública"
    },
    {
      "id": 34,
      "name": "Universidade Federal de Uberlândia (UFU)",
      "site": "https://www.ufu.br/",
      "state": "Minas Gerais",
      "type": "pública"
    },
    {
      "id": 35,
      "name": "Universidade Federal do Rio Grande (FURG)",
      "site": "https://www.furg.br/",
      "state": "Rio Grande do Sul",
      "type": "pública"
    },
    {
      "id": 36,
      "name": "Universidade Federal de Itajubá (UNIFEI)",
      "site": "https://www.unifei.edu.br/",
      "state": "Minas Gerais",
      "type": "pública"
    },
    {
      "id": 37,
      "name": "Universidade Federal do Pará (UFPA)",
      "site": "https://www.ufpa.br/",
      "state": "Pará",
      "type": "pública"
    },
    {
      "id": 38,
      "name": "Universidade Federal de São João del-Rei (UFSJ)",
      "site": "https://www.ufsj.edu.br/",
      "state": "Minas Gerais",
      "type": "pública"
    },
    {
      "id": 39,
      "name": "Universidade Federal de Lavras (UFLA)",
      "site": "https://ufla.br/",
      "state": "Minas Gerais",
      "type": "pública"
    },
    {
      "id": 40,
      "name": "Universidade Federal de Sergipe (UFS)",
      "site": "https://www.ufs.br/",
      "state": "Sergipe",
      "type": "pública"
    },
    {
      "id": 41,
      "name": "Universidade Federal do Tocantins (UFT)",
      "site": "https://ww2.uft.edu.br/",
      "state": "Tocantins",
      "type": "pública"
    },
    {
      "id": 42,
      "name": "Universidade Federal do Acre (UFAC)",
      "site": "https://www.ufac.br/",
      "state": "Acre",
      "type": "pública"
    },
    {
      "id": 43,
      "name": "Universidade Federal do Amapá (UNIFAP)",
      "site": "https://www.unifap.br/",
      "state": "Amapá",
      "type": "pública"
    },
    {
      "id": 44,
      "name": "Universidade Federal do Cariri (UFCA)",
      "site": "https://www.ufca.edu.br/",
      "state": "Ceará",
      "type": "pública"
    },
    {
      "id": 45,
      "name": "Universidade Federal do Maranhão (UFMA)",
      "site": "https://portais.ufma.br/",
      "state": "Maranhão",
      "type": "pública"
    },
    {
      "id": 46,
      "name": "Universidade Federal do Oeste da Bahia (UFOB)",
      "site": "https://www.ufob.edu.br/",
      "state": "Bahia",
      "type": "pública"
    },
    {
      "id": 47,
      "name": "Universidade Federal do Oeste do Pará (UFOPA)",
      "site": "https://www.ufopa.edu.br/",
      "state": "Pará",
      "type": "pública"
    },
    {
      "id": 48,
      "name": "Universidade Federal do Pampa (UNIPAMPA)",
      "site": "https://www.unipampa.edu.br/",
      "state": "Rio Grande do Sul",
      "type": "pública"
    },
    {
      "id": 49,
      "name": "Universidade Federal do Recôncavo da Bahia (UFRB)",
      "site": "https://www.ufrb.edu.br/",
      "state": "Bahia",
      "type": "pública"
    },
    {
      "id": 50,
      "name": "Universidade Federal do Sul e Sudeste do Pará (UNIFESSPA)",
      "site": "https://www.unifesspa.edu.br/",
      "state": "Pará",
      "type": "pública"
    },
    {
      "id": 51,
      "name": "Universidade Federal do Sul da Bahia (UFSB)",
      "site": "https://www.ufsb.edu.br/",
      "state": "Bahia",
      "type": "pública"
    },
    {
      "id": 53,
      "name": "Universidade de Fortaleza (UNIFOR)",
      "site": "https://www.unifor.br/",
      "state": "Ceará",
      "type": "privada"
    },
    {
      "id": 54,
      "name": "Universidade Presbiteriana Mackenzie (MACKENZIE)",
      "site": "https://www.mackenzie.br/",
      "state": "São Paulo",
      "type": "privada"
    },
    {
      "id": 55,
      "name": "Universidade Estácio de Sá (UNESA)",
      "site": "https://portal.estacio.br/",
      "state": "Rio de Janeiro",
      "type": "privada"
    },
    {
      "id": 56,
      "name": "Universidade do Vale do Rio dos Sinos (UNISINOS)",
      "site": "https://www.unisinos.br/",
      "state": "Rio Grande do Sul",
      "type": "privada"
    },
    {
      "id": 57,
      "name": "Universidade Feevale (FEEVALE)",
      "site": "https://www.feevale.br/",
      "state": "Rio Grande do Sul",
      "type": "privada"
    },
    {
      "id": 58,
      "name": "Universidade do Vale do Itajaí (UNIVALI)",
      "site": "https://www.univali.br/",
      "state": "Santa Catarina",
      "type": "privada"
    },
    {
      "id": 59,
      "name": "Universidade Católica de Brasília (UCB)",
      "site": "https://www.ucb.br/",
      "state": "Distrito Federal",
      "type": "privada"
    },
    {
      "id": 60,
      "name": "Universidade Salvador (UNIFACS)",
      "site": "https://www.unifacs.br/",
      "state": "Bahia",
      "type": "privada"
    },
    {
      "id": 61,
      "name": "Universidade do Vale do Paraíba (UNIVAP)",
      "site": "https://www.univap.br/",
      "state": "São Paulo",
      "type": "privada"
    },
    {
      "id": 62,
      "name": "Universidade Católica de Pernambuco (UNICAP)",
      "site": "https://www.unicap.br/",
      "state": "Pernambuco",
      "type": "privada"
    },
    {
      "id": 63,
      "name": "Universidade Anhembi Morumbi (UAM)",
      "site": "https://portal.anhembi.br/",
      "state": "São Paulo",
      "type": "privada"
    },
    {
      "id": 64,
      "name": "Universidade Positivo (UP)",
      "site": "https://www.up.edu.br/",
      "state": "Paraná",
      "type": "privada"
    },
    {
      "id": 65,
      "name": "Centro Universitário Senac",
      "site": "https://www.sp.senac.br/",
      "state": "São Paulo",
      "type": "privada"
    },
    {
      "id": 66,
      "name": "Universidade de Caxias do Sul (UCS)",
      "site": "https://www.ucs.br/",
      "state": "Rio Grande do Sul",
      "type": "privada"
    },
    {
      "id": 67,
      "name": "Universidade do Sul de Santa Catarina (UNISUL)",
      "site": "https://www.unisul.br/",
      "state": "Santa Catarina",
      "type": "privada"
    },
    {
      "id": 68,
      "name": "Pontifícia Universidade Católica de Minas Gerais (PUC Minas)",
      "site": "https://www.pucminas.br/",
      "state": "Minas Gerais",
      "type": "privada"
    },
    {
      "name": "Pontifícia Universidade Católica de Campinas (PUC CAMP)",
      "state": "São Paulo ",
      "site": "https://www.puc-campinas.edu.br",
      "type": "privada",
      "id": 69
    }
  ],
  "courses": [
    {
      "id": 1,
      "name": "Ciência da Computação",
      "acronym": "CC",
      "duration": 8,
      "schedule": "Integral",
      "curriculum": "https://www.ufmg.br/cc/graduacao/grade-curricular",
      "universityId": 3
    },
    {
      "id": 2,
      "name": "Sistemas de Informação",
      "acronym": "CC",
      "duration": 8,
      "schedule": "Integral",
      "curriculum": "https://www.ufmg.br/cc/graduacao/grade-curricular",
      "universityId": 4
    },
    {
      "name": "Processos administrativos",
      "acronym": "SI",
      "duration": "200",
      "schedule": "sempre",
      "curriculum": "ufmg.com",
      "universityId": "3",
      "id": 3
    },
    {
      "name": "Engenharia Civil",
      "acronym": "EC",
      "duration": "3600",
      "schedule": "Integral",
      "curriculum": "puc-campinas.br",
      "universityId": "69",
      "id": 4
    },
    {
      "name": "Direito",
      "acronym": "DIR",
      "duration": "3000",
      "schedule": "Noturno",
      "curriculum": "puc-campinas.br",
      "universityId": "69",
      "id": 5
    },
    {
      "name": "Administração",
      "acronym": "ADM",
      "duration": "2400",
      "schedule": "Noturno",
      "curriculum": "puc-campinas.br",
      "universityId": "69",
      "id": 6
    },
    {
      "name": "Medicina",
      "acronym": "MED",
      "duration": "4500",
      "schedule": "Integral",
      "curriculum": "puc-campinas.br",
      "universityId": "69",
      "id": 7
    },
    {
      "name": "Engenharia de Computação",
      "acronym": "ECOMP",
      "duration": "3600",
      "schedule": "Integral",
      "curriculum": "puc-campinas.br",
      "universityId": "69",
      "id": 8
    },
    {
      "name": "Arquitetura e Urbanismo",
      "acronym": "AU",
      "duration": "4000",
      "schedule": "Integral",
      "curriculum": "puc-campinas.br",
      "universityId": "69",
      "id": 9
    },
    {
      "name": "Ciências Contábeis",
      "acronym": "CC",
      "duration": "2400",
      "schedule": "Noturno",
      "curriculum": "puc-campinas.br",
      "universityId": "69",
      "id": 10
    },
    {
      "name": "Psicologia",
      "acronym": "PSI",
      "duration": "3000",
      "schedule": "Integral",
      "curriculum": "puc-campinas.br",
      "universityId": "69",
      "id": 11
    },
    {
      "name": "Jornalismo",
      "acronym": "JOR",
      "duration": "2400",
      "schedule": "Noturno",
      "curriculum": "puc-campinas.br",
      "universityId": "69",
      "id": 12
    },
    {
      "name": "Engenharia Elétrica",
      "acronym": "EE",
      "duration": "3600",
      "schedule": "Integral",
      "curriculum": "puc-campinas.br",
      "universityId": "69",
      "id": 13
    },
    {
      "name": "Engenharia Mecânica",
      "acronym": "EM",
      "duration": "3600",
      "schedule": "Integral",
      "curriculum": "pucminas.br",
      "universityId": "68",
      "id": 14
    },
    {
      "name": "Direito",
      "acronym": "DIR",
      "duration": "3000",
      "schedule": "Noturno",
      "curriculum": "pucminas.br",
      "universityId": "68",
      "id": 15
    },
    {
      "name": "Administração",
      "acronym": "ADM",
      "duration": "2400",
      "schedule": "Noturno",
      "curriculum": "pucminas.br",
      "universityId": "68",
      "id": 16
    },
    {
      "name": "Medicina",
      "acronym": "MED",
      "duration": "4500",
      "schedule": "Integral",
      "curriculum": "pucminas.br",
      "universityId": "68",
      "id": 17
    },
    {
      "name": "Engenharia de Computação",
      "acronym": "ECOMP",
      "duration": "3600",
      "schedule": "Integral",
      "curriculum": "pucminas.br",
      "universityId": "68",
      "id": 18
    },
    {
      "name": "Arquitetura e Urbanismo",
      "acronym": "AU",
      "duration": "4000",
      "schedule": "Integral",
      "curriculum": "pucminas.br",
      "universityId": "68",
      "id": 19
    },
    {
      "name": "Ciências Contábeis",
      "acronym": "CC",
      "duration": "2400",
      "schedule": "Noturno",
      "curriculum": "pucminas.br",
      "universityId": "68",
      "id": 20
    },
    {
      "name": "Psicologia",
      "acronym": "PSI",
      "duration": "3000",
      "schedule": "Integral",
      "curriculum": "pucminas.br",
      "universityId": "68",
      "id": 21
    },
    {
      "name": "Jornalismo",
      "acronym": "JOR",
      "duration": "2400",
      "schedule": "Noturno",
      "curriculum": "pucminas.br",
      "universityId": "68",
      "id": 22
    },
    {
      "name": "Engenharia Elétrica",
      "acronym": "EE",
      "duration": "3600",
      "schedule": "Integral",
      "curriculum": "pucminas.br",
      "universityId": "68",
      "id": 23
    },
    {
      "name": "Engenharia Civil",
      "acronym": "EC",
      "duration": "3600",
      "schedule": "Integral",
      "curriculum": "unisul.br",
      "universityId": "67",
      "id": 24
    },
    {
      "name": "Direito",
      "acronym": "DIR",
      "duration": "3000",
      "schedule": "Noturno",
      "curriculum": "unisul.br",
      "universityId": "67",
      "id": 25
    },
    {
      "name": "Administração",
      "acronym": "ADM",
      "duration": "2400",
      "schedule": "Noturno",
      "curriculum": "unisul.br",
      "universityId": "67",
      "id": 26
    },
    {
      "name": "Medicina",
      "acronym": "MED",
      "duration": "4500",
      "schedule": "Integral",
      "curriculum": "unisul.br",
      "universityId": "67",
      "id": 27
    },
    {
      "name": "Engenharia de Computação",
      "acronym": "ECOMP",
      "duration": "3600",
      "schedule": "Integral",
      "curriculum": "unisul.br",
      "universityId": "67",
      "id": 28
    },
    {
      "name": "Arquitetura e Urbanismo",
      "acronym": "AU",
      "duration": "4000",
      "schedule": "Integral",
      "curriculum": "unisul.br",
      "universityId": "67",
      "id": 29
    },
    {
      "name": "Ciências Contábeis",
      "acronym": "CC",
      "duration": "2400",
      "schedule": "Noturno",
      "curriculum": "unisul.br",
      "universityId": "67",
      "id": 30
    },
    {
      "name": "Psicologia",
      "acronym": "PSI",
      "duration": "3000",
      "schedule": "Integral",
      "curriculum": "unisul.br",
      "universityId": "67",
      "id": 31
    },
    {
      "name": "Jornalismo",
      "acronym": "JOR",
      "duration": "2400",
      "schedule": "Noturno",
      "curriculum": "unisul.br",
      "universityId": "67",
      "id": 32
    },
    {
      "name": "Engenharia Elétrica",
      "acronym": "EE",
      "duration": "3600",
      "schedule": "Integral",
      "curriculum": "unisul.br",
      "universityId": "67",
      "id": 33
    },
    {
      "name": "Engenharia Civil",
      "acronym": "EC",
      "duration": "3600",
      "schedule": "Integral",
      "curriculum": "ucs.br",
      "universityId": "66",
      "id": 34
    },
    {
      "name": "Direito",
      "acronym": "DIR",
      "duration": "3000",
      "schedule": "Noturno",
      "curriculum": "ucs.br",
      "universityId": "66",
      "id": 35
    },
    {
      "name": "Administração",
      "acronym": "ADM",
      "duration": "2400",
      "schedule": "Noturno",
      "curriculum": "ucs.br",
      "universityId": "66",
      "id": 36
    },
    {
      "name": "Medicina",
      "acronym": "MED",
      "duration": "4500",
      "schedule": "Integral",
      "curriculum": "ucs.br",
      "universityId": "66",
      "id": 37
    },
    {
      "name": "Engenharia de Computação",
      "acronym": "ECOMP",
      "duration": "3600",
      "schedule": "Integral",
      "curriculum": "ucs.br",
      "universityId": "66",
      "id": 38
    },
    {
      "name": "Arquitetura e Urbanismo",
      "acronym": "AU",
      "duration": "4000",
      "schedule": "Integral",
      "curriculum": "ucs.br",
      "universityId": "66",
      "id": 39
    },
    {
      "name": "Ciências Contábeis",
      "acronym": "CC",
      "duration": "2400",
      "schedule": "Noturno",
      "curriculum": "ucs.br",
      "universityId": "66",
      "id": 40
    },
    {
      "name": "Psicologia",
      "acronym": "PSI",
      "duration": "3000",
      "schedule": "Integral",
      "curriculum": "ucs.br",
      "universityId": "66",
      "id": 41
    },
    {
      "name": "Jornalismo",
      "acronym": "JOR",
      "duration": "2400",
      "schedule": "Noturno",
      "curriculum": "ucs.br",
      "universityId": "66",
      "id": 42
    },
    {
      "name": "Engenharia Elétrica",
      "acronym": "EE",
      "duration": "3600",
      "schedule": "Integral",
      "curriculum": "ucs.br",
      "universityId": "66",
      "id": 43
    },
    {
      "name": "Gastronomia",
      "acronym": "GASTRO",
      "duration": "2400",
      "schedule": "Integral",
      "curriculum": "sp.senac.br",
      "universityId": "65",
      "id": 44
    },
    {
      "name": "Hotelaria",
      "acronym": "HOT",
      "duration": "2400",
      "schedule": "Integral",
      "curriculum": "sp.senac.br",
      "universityId": "65",
      "id": 45
    },
    {
      "name": "Design de Interiores",
      "acronym": "DI",
      "duration": "2400",
      "schedule": "Noturno",
      "curriculum": "sp.senac.br",
      "universityId": "65",
      "id": 46
    },
    {
      "name": "Engenharia de Produção",
      "acronym": "EP",
      "duration": "3600",
      "schedule": "Integral",
      "curriculum": "sp.senac.br",
      "universityId": "65",
      "id": 47
    },
    {
      "name": "Ciência da Computação",
      "acronym": "CC",
      "duration": "3600",
      "schedule": "Integral",
      "curriculum": "sp.senac.br",
      "universityId": "65",
      "id": 48
    },
    {
      "name": "Fotografia",
      "acronym": "FOTO",
      "duration": "2400",
      "schedule": "Noturno",
      "curriculum": "sp.senac.br",
      "universityId": "65",
      "id": 49
    },
    {
      "name": "Marketing",
      "acronym": "MKT",
      "duration": "2400",
      "schedule": "Noturno",
      "curriculum": "sp.senac.br",
      "universityId": "65",
      "id": 50
    },
    {
      "name": "Administração",
      "acronym": "ADM",
      "duration": "2400",
      "schedule": "Noturno",
      "curriculum": "sp.senac.br",
      "universityId": "65",
      "id": 51
    },
    {
      "name": "Educação Física",
      "acronym": "EF",
      "duration": "3000",
      "schedule": "Integral",
      "curriculum": "sp.senac.br",
      "universityId": "65",
      "id": 52
    },
    {
      "name": "Moda",
      "acronym": "MODA",
      "duration": "2400",
      "schedule": "Integral",
      "curriculum": "sp.senac.br",
      "universityId": "65",
      "id": 53
    },
    {
      "name": "Medicina",
      "acronym": "MED",
      "duration": "4500",
      "schedule": "Integral",
      "curriculum": "up.edu.br",
      "universityId": "64",
      "id": 54
    },
    {
      "name": "Direito",
      "acronym": "DIR",
      "duration": "3000",
      "schedule": "Noturno",
      "curriculum": "up.edu.br",
      "universityId": "64",
      "id": 55
    },
    {
      "name": "Engenharia Civil",
      "acronym": "EC",
      "duration": "3600",
      "schedule": "Integral",
      "curriculum": "up.edu.br",
      "universityId": "64",
      "id": 56
    },
    {
      "name": "Administração",
      "acronym": "ADM",
      "duration": "2400",
      "schedule": "Noturno",
      "curriculum": "up.edu.br",
      "universityId": "64",
      "id": 57
    },
    {
      "name": "Psicologia",
      "acronym": "PSI",
      "duration": "3000",
      "schedule": "Integral",
      "curriculum": "up.edu.br",
      "universityId": "64",
      "id": 58
    },
    {
      "name": "Engenharia de Software",
      "acronym": "ES",
      "duration": "3600",
      "schedule": "Integral",
      "curriculum": "up.edu.br",
      "universityId": "64",
      "id": 59
    },
    {
      "name": "Arquitetura e Urbanismo",
      "acronym": "AU",
      "duration": "4000",
      "schedule": "Integral",
      "curriculum": "up.edu.br",
      "universityId": "64",
      "id": 60
    },
    {
      "name": "Biomedicina",
      "acronym": "BIO",
      "duration": "2400",
      "schedule": "Integral",
      "curriculum": "up.edu.br",
      "universityId": "64",
      "id": 61
    },
    {
      "name": "Design Gráfico",
      "acronym": "DG",
      "duration": "2400",
      "schedule": "Noturno",
      "curriculum": "up.edu.br",
      "universityId": "64",
      "id": 62
    },
    {
      "name": "Educação Física",
      "acronym": "EF",
      "duration": "3000",
      "schedule": "Integral",
      "curriculum": "up.edu.br",
      "universityId": "64",
      "id": 63
    },
    {
      "name": "Medicina",
      "acronym": "MED",
      "duration": "4500",
      "schedule": "Integral",
      "curriculum": "anhembi.br",
      "universityId": "63",
      "id": 64
    },
    {
      "name": "Direito",
      "acronym": "DIR",
      "duration": "3000",
      "schedule": "Noturno",
      "curriculum": "anhembi.br",
      "universityId": "63",
      "id": 65
    },
    {
      "name": "Engenharia Civil",
      "acronym": "EC",
      "duration": "3600",
      "schedule": "Integral",
      "curriculum": "anhembi.br",
      "universityId": "63",
      "id": 66
    },
    {
      "name": "Administração",
      "acronym": "ADM",
      "duration": "2400",
      "schedule": "Noturno",
      "curriculum": "anhembi.br",
      "universityId": "63",
      "id": 67
    },
    {
      "name": "Psicologia",
      "acronym": "PSI",
      "duration": "3000",
      "schedule": "Integral",
      "curriculum": "anhembi.br",
      "universityId": "63",
      "id": 68
    },
    {
      "name": "Engenharia de Software",
      "acronym": "ES",
      "duration": "3600",
      "schedule": "Integral",
      "curriculum": "anhembi.br",
      "universityId": "63",
      "id": 69
    },
    {
      "name": "Arquitetura e Urbanismo",
      "acronym": "AU",
      "duration": "4000",
      "schedule": "Integral",
      "curriculum": "anhembi.br",
      "universityId": "63",
      "id": 70
    },
    {
      "name": "Biomedicina",
      "acronym": "BIO",
      "duration": "2400",
      "schedule": "Integral",
      "curriculum": "anhembi.br",
      "universityId": "63",
      "id": 71
    },
    {
      "name": "Design Gráfico",
      "acronym": "DG",
      "duration": "2400",
      "schedule": "Noturno",
      "curriculum": "anhembi.br",
      "universityId": "63",
      "id": 72
    },
    {
      "name": "Educação Física",
      "acronym": "EF",
      "duration": "3000",
      "schedule": "Integral",
      "curriculum": "anhembi.br",
      "universityId": "63",
      "id": 73
    },
    {
      "name": "Medicina",
      "acronym": "MED",
      "duration": "4500",
      "schedule": "Integral",
      "curriculum": "unicap.br",
      "universityId": "62",
      "id": 74
    },
    {
      "name": "Direito",
      "acronym": "DIR",
      "duration": "3000",
      "schedule": "Noturno",
      "curriculum": "unicap.br",
      "universityId": "62",
      "id": 75
    },
    {
      "name": "Engenharia Civil",
      "acronym": "EC",
      "duration": "3600",
      "schedule": "Integral",
      "curriculum": "unicap.br",
      "universityId": "62",
      "id": 76
    },
    {
      "name": "Administração",
      "acronym": "ADM",
      "duration": "2400",
      "schedule": "Noturno",
      "curriculum": "unicap.br",
      "universityId": "62",
      "id": 77
    },
    {
      "name": "Psicologia",
      "acronym": "PSI",
      "duration": "3000",
      "schedule": "Integral",
      "curriculum": "unicap.br",
      "universityId": "62",
      "id": 78
    },
    {
      "name": "Engenharia de Software",
      "acronym": "ES",
      "duration": "3600",
      "schedule": "Integral",
      "curriculum": "unicap.br",
      "universityId": "62",
      "id": 79
    },
    {
      "name": "Arquitetura e Urbanismo",
      "acronym": "AU",
      "duration": "4000",
      "schedule": "Integral",
      "curriculum": "unicap.br",
      "universityId": "62",
      "id": 80
    },
    {
      "name": "Biomedicina",
      "acronym": "BIO",
      "duration": "2400",
      "schedule": "Integral",
      "curriculum": "unicap.br",
      "universityId": "62",
      "id": 81
    },
    {
      "name": "Design Gráfico",
      "acronym": "DG",
      "duration": "2400",
      "schedule": "Noturno",
      "curriculum": "unicap.br",
      "universityId": "62",
      "id": 82
    },
    {
      "name": "Educação Física",
      "acronym": "EF",
      "duration": "3000",
      "schedule": "Integral",
      "curriculum": "unicap.br",
      "universityId": "62",
      "id": 83
    },
    {
      "name": "Medicina",
      "acronym": "MED",
      "duration": "4500",
      "schedule": "Integral",
      "curriculum": "univap.br",
      "universityId": "61",
      "id": 84
    },
    {
      "name": "Direito",
      "acronym": "DIR",
      "duration": "3000",
      "schedule": "Noturno",
      "curriculum": "univap.br",
      "universityId": "61",
      "id": 85
    },
    {
      "name": "Engenharia Civil",
      "acronym": "EC",
      "duration": "3600",
      "schedule": "Integral",
      "curriculum": "univap.br",
      "universityId": "61",
      "id": 86
    },
    {
      "name": "Administração",
      "acronym": "ADM",
      "duration": "2400",
      "schedule": "Noturno",
      "curriculum": "univap.br",
      "universityId": "61",
      "id": 87
    },
    {
      "name": "Psicologia",
      "acronym": "PSI",
      "duration": "3000",
      "schedule": "Integral",
      "curriculum": "univap.br",
      "universityId": "61",
      "id": 88
    },
    {
      "name": "Engenharia de Software",
      "acronym": "ES",
      "duration": "3600",
      "schedule": "Integral",
      "curriculum": "univap.br",
      "universityId": "61",
      "id": 89
    },
    {
      "name": "Arquitetura e Urbanismo",
      "acronym": "AU",
      "duration": "4000",
      "schedule": "Integral",
      "curriculum": "univap.br",
      "universityId": "61",
      "id": 90
    },
    {
      "name": "Biomedicina",
      "acronym": "BIO",
      "duration": "2400",
      "schedule": "Integral",
      "curriculum": "univap.br",
      "universityId": "61",
      "id": 91
    },
    {
      "name": "Design Gráfico",
      "acronym": "DG",
      "duration": "2400",
      "schedule": "Noturno",
      "curriculum": "univap.br",
      "universityId": "61",
      "id": 92
    },
    {
      "name": "Educação Física",
      "acronym": "EF",
      "duration": "3000",
      "schedule": "Integral",
      "curriculum": "univap.br",
      "universityId": "61",
      "id": 93
    },
    {
      "name": "Medicina",
      "acronym": "MED",
      "duration": "4500",
      "schedule": "Integral",
      "curriculum": "unifacs.br",
      "universityId": "60",
      "id": 94
    },
    {
      "name": "Direito",
      "acronym": "DIR",
      "duration": "3000",
      "schedule": "Noturno",
      "curriculum": "unifacs.br",
      "universityId": "60",
      "id": 95
    },
    {
      "name": "Engenharia Civil",
      "acronym": "EC",
      "duration": "3600",
      "schedule": "Integral",
      "curriculum": "unifacs.br",
      "universityId": "60",
      "id": 96
    },
    {
      "name": "Administração",
      "acronym": "ADM",
      "duration": "2400",
      "schedule": "Noturno",
      "curriculum": "unifacs.br",
      "universityId": "60",
      "id": 97
    },
    {
      "name": "Psicologia",
      "acronym": "PSI",
      "duration": "3000",
      "schedule": "Integral",
      "curriculum": "unifacs.br",
      "universityId": "60",
      "id": 98
    },
    {
      "name": "Engenharia de Software",
      "acronym": "ES",
      "duration": "3600",
      "schedule": "Integral",
      "curriculum": "unifacs.br",
      "universityId": "60",
      "id": 99
    },
    {
      "name": "Arquitetura e Urbanismo",
      "acronym": "AU",
      "duration": "4000",
      "schedule": "Integral",
      "curriculum": "unifacs.br",
      "universityId": "60",
      "id": 100
    },
    {
      "name": "Biomedicina",
      "acronym": "BIO",
      "duration": "2400",
      "schedule": "Integral",
      "curriculum": "unifacs.br",
      "universityId": "60",
      "id": 101
    },
    {
      "name": "Design Gráfico",
      "acronym": "DG",
      "duration": "2400",
      "schedule": "Noturno",
      "curriculum": "unifacs.br",
      "universityId": "60",
      "id": 102
    },
    {
      "name": "Educação Física",
      "acronym": "EF",
      "duration": "3000",
      "schedule": "Integral",
      "curriculum": "unifacs.br",
      "universityId": "60",
      "id": 103
    },
    {
      "name": "Medicina",
      "acronym": "MED",
      "duration": "4500",
      "schedule": "Integral",
      "curriculum": "ucb.br",
      "universityId": "59",
      "id": 104
    },
    {
      "name": "Direito",
      "acronym": "DIR",
      "duration": "3000",
      "schedule": "Noturno",
      "curriculum": "ucb.br",
      "universityId": "59",
      "id": 105
    },
    {
      "name": "Engenharia Civil",
      "acronym": "EC",
      "duration": "3600",
      "schedule": "Integral",
      "curriculum": "ucb.br",
      "universityId": "59",
      "id": 106
    },
    {
      "name": "Administração",
      "acronym": "ADM",
      "duration": "2400",
      "schedule": "Noturno",
      "curriculum": "ucb.br",
      "universityId": "59",
      "id": 107
    },
    {
      "name": "Psicologia",
      "acronym": "PSI",
      "duration": "3000",
      "schedule": "Integral",
      "curriculum": "ucb.br",
      "universityId": "59",
      "id": 108
    },
    {
      "name": "Engenharia de Software",
      "acronym": "ES",
      "duration": "3600",
      "schedule": "Integral",
      "curriculum": "ucb.br",
      "universityId": "59",
      "id": 109
    },
    {
      "name": "Arquitetura e Urbanismo",
      "acronym": "AU",
      "duration": "4000",
      "schedule": "Integral",
      "curriculum": "ucb.br",
      "universityId": "59",
      "id": 110
    },
    {
      "name": "Biomedicina",
      "acronym": "BIO",
      "duration": "2400",
      "schedule": "Integral",
      "curriculum": "ucb.br",
      "universityId": "59",
      "id": 111
    },
    {
      "name": "Design Gráfico",
      "acronym": "DG",
      "duration": "2400",
      "schedule": "Noturno",
      "curriculum": "ucb.br",
      "universityId": "59",
      "id": 112
    },
    {
      "name": "Educação Física",
      "acronym": "EF",
      "duration": "3000",
      "schedule": "Integral",
      "curriculum": "ucb.br",
      "universityId": "59",
      "id": 113
    },
    {
      "name": "Medicina",
      "acronym": "MED",
      "duration": "4500",
      "schedule": "Integral",
      "curriculum": "univali.br",
      "universityId": "58",
      "id": 114
    },
    {
      "name": "Direito",
      "acronym": "DIR",
      "duration": "3000",
      "schedule": "Noturno",
      "curriculum": "univali.br",
      "universityId": "58",
      "id": 115
    },
    {
      "name": "Engenharia Civil",
      "acronym": "EC",
      "duration": "3600",
      "schedule": "Integral",
      "curriculum": "univali.br",
      "universityId": "58",
      "id": 116
    },
    {
      "name": "Administração",
      "acronym": "ADM",
      "duration": "2400",
      "schedule": "Noturno",
      "curriculum": "univali.br",
      "universityId": "58",
      "id": 117
    },
    {
      "name": "Psicologia",
      "acronym": "PSI",
      "duration": "3000",
      "schedule": "Integral",
      "curriculum": "univali.br",
      "universityId": "58",
      "id": 118
    },
    {
      "name": "Engenharia de Software",
      "acronym": "ES",
      "duration": "3600",
      "schedule": "Integral",
      "curriculum": "univali.br",
      "universityId": "58",
      "id": 119
    },
    {
      "name": "Arquitetura e Urbanismo",
      "acronym": "AU",
      "duration": "4000",
      "schedule": "Integral",
      "curriculum": "univali.br",
      "universityId": "58",
      "id": 120
    },
    {
      "name": "Biomedicina",
      "acronym": "BIO",
      "duration": "2400",
      "schedule": "Integral",
      "curriculum": "univali.br",
      "universityId": "58",
      "id": 121
    },
    {
      "name": "Design Gráfico",
      "acronym": "DG",
      "duration": "2400",
      "schedule": "Noturno",
      "curriculum": "univali.br",
      "universityId": "58",
      "id": 122
    },
    {
      "name": "Educação Física",
      "acronym": "EF",
      "duration": "3000",
      "schedule": "Integral",
      "curriculum": "univali.br",
      "universityId": "58",
      "id": 123
    },
    {
      "name": "Medicina",
      "acronym": "MED",
      "duration": "4500",
      "schedule": "Integral",
      "curriculum": "feevale.br",
      "universityId": "57",
      "id": 124
    },
    {
      "name": "Direito",
      "acronym": "DIR",
      "duration": "3000",
      "schedule": "Noturno",
      "curriculum": "feevale.br",
      "universityId": "57",
      "id": 125
    },
    {
      "name": "Engenharia Civil",
      "acronym": "EC",
      "duration": "3600",
      "schedule": "Integral",
      "curriculum": "feevale.br",
      "universityId": "57",
      "id": 126
    },
    {
      "name": "Administração",
      "acronym": "ADM",
      "duration": "2400",
      "schedule": "Noturno",
      "curriculum": "feevale.br",
      "universityId": "57",
      "id": 127
    },
    {
      "name": "Psicologia",
      "acronym": "PSI",
      "duration": "3000",
      "schedule": "Integral",
      "curriculum": "feevale.br",
      "universityId": "57",
      "id": 128
    },
    {
      "name": "Engenharia de Software",
      "acronym": "ES",
      "duration": "3600",
      "schedule": "Integral",
      "curriculum": "feevale.br",
      "universityId": "57",
      "id": 129
    },
    {
      "name": "Arquitetura e Urbanismo",
      "acronym": "AU",
      "duration": "4000",
      "schedule": "Integral",
      "curriculum": "feevale.br",
      "universityId": "57",
      "id": 130
    },
    {
      "name": "Biomedicina",
      "acronym": "BIO",
      "duration": "2400",
      "schedule": "Integral",
      "curriculum": "feevale.br",
      "universityId": "57",
      "id": 131
    },
    {
      "name": "Design Gráfico",
      "acronym": "DG",
      "duration": "2400",
      "schedule": "Noturno",
      "curriculum": "feevale.br",
      "universityId": "57",
      "id": 132
    },
    {
      "name": "Educação Física",
      "acronym": "EF",
      "duration": "3000",
      "schedule": "Integral",
      "curriculum": "feevale.br",
      "universityId": "57",
      "id": 133
    },
    {
      "name": "Medicina",
      "acronym": "MED",
      "duration": "4500",
      "schedule": "Integral",
      "curriculum": "unisinos.br",
      "universityId": "56",
      "id": 134
    },
    {
      "name": "Direito",
      "acronym": "DIR",
      "duration": "3000",
      "schedule": "Noturno",
      "curriculum": "unisinos.br",
      "universityId": "56",
      "id": 135
    },
    {
      "name": "Engenharia Civil",
      "acronym": "EC",
      "duration": "3600",
      "schedule": "Integral",
      "curriculum": "unisinos.br",
      "universityId": "56",
      "id": 136
    },
    {
      "name": "Administração",
      "acronym": "ADM",
      "duration": "2400",
      "schedule": "Noturno",
      "curriculum": "unisinos.br",
      "universityId": "56",
      "id": 137
    },
    {
      "name": "Psicologia",
      "acronym": "PSI",
      "duration": "3000",
      "schedule": "Integral",
      "curriculum": "unisinos.br",
      "universityId": "56",
      "id": 138
    },
    {
      "name": "Engenharia de Software",
      "acronym": "ES",
      "duration": "3600",
      "schedule": "Integral",
      "curriculum": "unisinos.br",
      "universityId": "56",
      "id": 139
    },
    {
      "name": "Arquitetura e Urbanismo",
      "acronym": "AU",
      "duration": "4000",
      "schedule": "Integral",
      "curriculum": "unisinos.br",
      "universityId": "56",
      "id": 140
    },
    {
      "name": "Biomedicina",
      "acronym": "BIO",
      "duration": "2400",
      "schedule": "Integral",
      "curriculum": "unisinos.br",
      "universityId": "56",
      "id": 141
    },
    {
      "name": "Design Gráfico",
      "acronym": "DG",
      "duration": "2400",
      "schedule": "Noturno",
      "curriculum": "unisinos.br",
      "universityId": "56",
      "id": 142
    },
    {
      "name": "Educação Física",
      "acronym": "EF",
      "duration": "3000",
      "schedule": "Integral",
      "curriculum": "unisinos.br",
      "universityId": "56",
      "id": 143
    },
    {
      "name": "Medicina",
      "acronym": "MED",
      "duration": "4500",
      "schedule": "Integral",
      "curriculum": "estacio.br",
      "universityId": "55",
      "id": 144
    },
    {
      "name": "Direito",
      "acronym": "DIR",
      "duration": "3000",
      "schedule": "Noturno",
      "curriculum": "estacio.br",
      "universityId": "55",
      "id": 145
    },
    {
      "name": "Engenharia Civil",
      "acronym": "EC",
      "duration": "3600",
      "schedule": "Integral",
      "curriculum": "estacio.br",
      "universityId": "55",
      "id": 146
    },
    {
      "name": "Administração",
      "acronym": "ADM",
      "duration": "2400",
      "schedule": "Noturno",
      "curriculum": "estacio.br",
      "universityId": "55",
      "id": 147
    },
    {
      "name": "Psicologia",
      "acronym": "PSI",
      "duration": "3000",
      "schedule": "Integral",
      "curriculum": "estacio.br",
      "universityId": "55",
      "id": 148
    },
    {
      "name": "Engenharia de Software",
      "acronym": "ES",
      "duration": "3600",
      "schedule": "Integral",
      "curriculum": "estacio.br",
      "universityId": "55",
      "id": 149
    },
    {
      "name": "Arquitetura e Urbanismo",
      "acronym": "AU",
      "duration": "4000",
      "schedule": "Integral",
      "curriculum": "estacio.br",
      "universityId": "55",
      "id": 150
    },
    {
      "name": "Biomedicina",
      "acronym": "BIO",
      "duration": "2400",
      "schedule": "Integral",
      "curriculum": "estacio.br",
      "universityId": "55",
      "id": 151
    },
    {
      "name": "Design Gráfico",
      "acronym": "DG",
      "duration": "2400",
      "schedule": "Noturno",
      "curriculum": "estacio.br",
      "universityId": "55",
      "id": 152
    },
    {
      "name": "Educação Física",
      "acronym": "EF",
      "duration": "3000",
      "schedule": "Integral",
      "curriculum": "estacio.br",
      "universityId": "55",
      "id": 153
    },
    {
      "name": "Medicina",
      "acronym": "MED",
      "duration": "4500",
      "schedule": "Integral",
      "curriculum": "mackenzie.br",
      "universityId": "54",
      "id": 154
    },
    {
      "name": "Direito",
      "acronym": "DIR",
      "duration": "3000",
      "schedule": "Noturno",
      "curriculum": "mackenzie.br",
      "universityId": "54",
      "id": 155
    },
    {
      "name": "Engenharia Civil",
      "acronym": "EC",
      "duration": "3600",
      "schedule": "Integral",
      "curriculum": "mackenzie.br",
      "universityId": "54",
      "id": 156
    },
    {
      "name": "Administração",
      "acronym": "ADM",
      "duration": "2400",
      "schedule": "Noturno",
      "curriculum": "mackenzie.br",
      "universityId": "54",
      "id": 157
    },
    {
      "name": "Psicologia",
      "acronym": "PSI",
      "duration": "3000",
      "schedule": "Integral",
      "curriculum": "mackenzie.br",
      "universityId": "54",
      "id": 158
    },
    {
      "name": "Engenharia de Software",
      "acronym": "ES",
      "duration": "3600",
      "schedule": "Integral",
      "curriculum": "mackenzie.br",
      "universityId": "54",
      "id": 159
    },
    {
      "name": "Arquitetura e Urbanismo",
      "acronym": "AU",
      "duration": "4000",
      "schedule": "Integral",
      "curriculum": "mackenzie.br",
      "universityId": "54",
      "id": 160
    },
    {
      "name": "Biomedicina",
      "acronym": "BIO",
      "duration": "2400",
      "schedule": "Integral",
      "curriculum": "mackenzie.br",
      "universityId": "54",
      "id": 161
    },
    {
      "name": "Design Gráfico",
      "acronym": "DG",
      "duration": "2400",
      "schedule": "Noturno",
      "curriculum": "mackenzie.br",
      "universityId": "54",
      "id": 162
    },
    {
      "name": "Educação Física",
      "acronym": "EF",
      "duration": "3000",
      "schedule": "Integral",
      "curriculum": "mackenzie.br",
      "universityId": "54",
      "id": 163
    },
    {
      "name": "Medicina",
      "acronym": "MED",
      "duration": "4500",
      "schedule": "Integral",
      "curriculum": "unifor.br",
      "universityId": "53",
      "id": 164
    },
    {
      "name": "Direito",
      "acronym": "DIR",
      "duration": "3000",
      "schedule": "Noturno",
      "curriculum": "unifor.br",
      "universityId": "53",
      "id": 165
    },
    {
      "name": "Engenharia Civil",
      "acronym": "EC",
      "duration": "3600",
      "schedule": "Integral",
      "curriculum": "unifor.br",
      "universityId": "53",
      "id": 166
    },
    {
      "name": "Administração",
      "acronym": "ADM",
      "duration": "2400",
      "schedule": "Noturno",
      "curriculum": "unifor.br",
      "universityId": "53",
      "id": 167
    },
    {
      "name": "Psicologia",
      "acronym": "PSI",
      "duration": "3000",
      "schedule": "Integral",
      "curriculum": "unifor.br",
      "universityId": "53",
      "id": 168
    },
    {
      "name": "Engenharia de Software",
      "acronym": "ES",
      "duration": "3600",
      "schedule": "Integral",
      "curriculum": "unifor.br",
      "universityId": "53",
      "id": 169
    },
    {
      "name": "Arquitetura e Urbanismo",
      "acronym": "AU",
      "duration": "4000",
      "schedule": "Integral",
      "curriculum": "unifor.br",
      "universityId": "53",
      "id": 170
    },
    {
      "name": "Biomedicina",
      "acronym": "BIO",
      "duration": "2400",
      "schedule": "Integral",
      "curriculum": "unifor.br",
      "universityId": "53",
      "id": 171
    },
    {
      "name": "Design Gráfico",
      "acronym": "DG",
      "duration": "2400",
      "schedule": "Noturno",
      "curriculum": "unifor.br",
      "universityId": "53",
      "id": 172
    },
    {
      "name": "Educação Física",
      "acronym": "EF",
      "duration": "3000",
      "schedule": "Integral",
      "curriculum": "unifor.br",
      "universityId": "53",
      "id": 173
    }
  ]
}